[
    {
        "district": "1",
        "costs-shared": 34306
    },
    {
        "location": "3,45",
        "capacity": 1507.0,
        "houses": [
            {
                "location": "49,44",
                "output": 39.82123377,
                "cables": [
                    "49,44",
                    "49,45",
                    "49,46",
                    "49,47",
                    "49,48",
                    "49,49",
                    "49,50"
                ]
            },
            {
                "location": "22,46",
                "output": 62.43058175,
                "cables": [
                    "22,46",
                    "22,47",
                    "21,47",
                    "20,47",
                    "19,47",
                    "18,47",
                    "17,47",
                    "16,47",
                    "15,47"
                ]
            },
            {
                "location": "20,11",
                "output": 40.20336825,
                "cables": [
                    "20,11",
                    "20,12",
                    "19,12"
                ]
            },
            {
                "location": "19,12",
                "output": 53.03976583,
                "cables": [
                    "19,12",
                    "18,12",
                    "17,12",
                    "16,12",
                    "15,12",
                    "14,12",
                    "13,12",
                    "12,12",
                    "11,12",
                    "10,12",
                    "9,12",
                    "8,12",
                    "7,12",
                    "6,12",
                    "5,12"
                ]
            },
            {
                "location": "33,0",
                "output": 39.13247939,
                "cables": [
                    "33,0",
                    "33,1",
                    "33,2",
                    "33,3",
                    "32,3",
                    "31,3",
                    "30,3",
                    "29,3",
                    "28,3"
                ]
            },
            {
                "location": "37,23",
                "output": 51.94608562,
                "cables": [
                    "37,23",
                    "37,22",
                    "37,21",
                    "37,20",
                    "37,19",
                    "37,18",
                    "37,17",
                    "37,16",
                    "37,15",
                    "37,14"
                ]
            },
            {
                "location": "13,27",
                "output": 37.28002017,
                "cables": [
                    "13,27",
                    "13,28"
                ]
            },
            {
                "location": "41,36",
                "output": 60.96696147,
                "cables": [
                    "41,36",
                    "41,37",
                    "41,38",
                    "41,39",
                    "42,39",
                    "43,39"
                ]
            },
            {
                "location": "48,50",
                "output": 35.97663002,
                "cables": [
                    "48,50",
                    "47,50",
                    "46,50",
                    "45,50",
                    "44,50",
                    "43,50",
                    "42,50",
                    "41,50",
                    "40,50",
                    "39,50",
                    "38,50",
                    "37,50",
                    "36,50",
                    "35,50",
                    "34,50"
                ]
            },
            {
                "location": "5,13",
                "output": 57.19809379,
                "cables": [
                    "5,13",
                    "5,14",
                    "5,15",
                    "5,16",
                    "5,17",
                    "5,18",
                    "5,19",
                    "5,20",
                    "5,21",
                    "5,22",
                    "5,23",
                    "5,24"
                ]
            },
            {
                "location": "46,42",
                "output": 66.07952654,
                "cables": [
                    "46,42",
                    "46,43",
                    "46,44",
                    "47,44",
                    "48,44",
                    "49,44"
                ]
            },
            {
                "location": "2,12",
                "output": 75.8473443,
                "cables": [
                    "2,12",
                    "2,13",
                    "3,13",
                    "4,13",
                    "5,13"
                ]
            },
            {
                "location": "5,9",
                "output": 38.37311881,
                "cables": [
                    "5,9",
                    "5,10",
                    "5,11",
                    "5,12",
                    "5,13"
                ]
            },
            {
                "location": "13,28",
                "output": 56.14106998,
                "cables": [
                    "13,28",
                    "14,28",
                    "15,28",
                    "16,28",
                    "17,28",
                    "18,28"
                ]
            },
            {
                "location": "15,50",
                "output": 47.17876571,
                "cables": [
                    "15,50",
                    "15,49",
                    "15,48",
                    "15,47",
                    "14,47",
                    "13,47",
                    "12,47",
                    "11,47",
                    "10,47"
                ]
            },
            {
                "location": "18,28",
                "output": 55.75694271,
                "cables": [
                    "18,28",
                    "18,29",
                    "18,30",
                    "18,31",
                    "18,32"
                ]
            },
            {
                "location": "43,14",
                "output": 59.68412189,
                "cables": [
                    "43,14",
                    "42,14",
                    "41,14",
                    "40,14",
                    "39,14",
                    "38,14",
                    "37,14",
                    "36,14",
                    "35,14",
                    "34,14",
                    "33,14",
                    "32,14",
                    "31,14",
                    "30,14",
                    "29,14",
                    "28,14"
                ]
            },
            {
                "location": "43,39",
                "output": 30.57764452,
                "cables": [
                    "43,39",
                    "44,39",
                    "45,39",
                    "46,39"
                ]
            },
            {
                "location": "21,44",
                "output": 46.65642768,
                "cables": [
                    "21,44",
                    "21,45",
                    "21,46",
                    "21,47"
                ]
            },
            {
                "location": "10,47",
                "output": 70.68631843,
                "cables": [
                    "10,47",
                    "10,46",
                    "10,45",
                    "9,45",
                    "8,45",
                    "7,45",
                    "6,45",
                    "5,45",
                    "4,45",
                    "3,45"
                ]
            },
            {
                "location": "18,32",
                "output": 32.63123071,
                "cables": [
                    "18,32",
                    "18,33",
                    "18,34",
                    "18,35",
                    "18,36",
                    "18,37",
                    "18,38",
                    "18,39",
                    "18,40",
                    "18,41",
                    "18,42",
                    "18,43",
                    "18,44",
                    "18,45",
                    "18,46",
                    "18,47"
                ]
            },
            {
                "location": "5,37",
                "output": 68.63304898,
                "cables": [
                    "5,37",
                    "5,38",
                    "5,39",
                    "5,40",
                    "5,41",
                    "5,42",
                    "5,43",
                    "5,44",
                    "5,45"
                ]
            },
            {
                "location": "34,50",
                "output": 41.71675352,
                "cables": [
                    "34,50",
                    "34,49",
                    "34,48",
                    "34,47",
                    "33,47",
                    "32,47",
                    "31,47",
                    "30,47",
                    "29,47",
                    "28,47",
                    "27,47",
                    "26,47",
                    "25,47",
                    "24,47",
                    "23,47",
                    "22,47"
                ]
            },
            {
                "location": "28,3",
                "output": 29.90737428,
                "cables": [
                    "28,3",
                    "28,4",
                    "28,5",
                    "28,6",
                    "28,7",
                    "29,7"
                ]
            },
            {
                "location": "28,15",
                "output": 37.81128037,
                "cables": [
                    "28,15",
                    "28,14",
                    "28,13",
                    "28,12",
                    "27,12",
                    "26,12",
                    "25,12",
                    "24,12",
                    "23,12",
                    "22,12",
                    "21,12",
                    "20,12"
                ]
            },
            {
                "location": "46,38",
                "output": 73.40226925,
                "cables": [
                    "46,38",
                    "46,39",
                    "46,40",
                    "46,41",
                    "46,42"
                ]
            },
            {
                "location": "1,24",
                "output": 54.40644245,
                "cables": [
                    "1,24",
                    "2,24",
                    "3,24",
                    "4,24",
                    "5,24",
                    "6,24",
                    "7,24",
                    "8,24",
                    "9,24"
                ]
            },
            {
                "location": "9,23",
                "output": 29.43663895,
                "cables": [
                    "9,23",
                    "9,24",
                    "9,25",
                    "9,26",
                    "9,27",
                    "10,27",
                    "11,27",
                    "12,27",
                    "13,27"
                ]
            },
            {
                "location": "50,49",
                "output": 38.24420236,
                "cables": [
                    "50,49",
                    "50,50",
                    "49,50",
                    "48,50"
                ]
            },
            {
                "location": "29,7",
                "output": 60.8375359,
                "cables": [
                    "29,7",
                    "29,8",
                    "29,9",
                    "29,10",
                    "29,11",
                    "29,12",
                    "28,12"
                ]
            }
        ]
    },
    {
        "location": "38,12",
        "capacity": 1507.0,
        "houses": [
            {
                "location": "34,47",
                "output": 53.97543253,
                "cables": [
                    "34,47",
                    "34,46",
                    "34,45",
                    "34,44",
                    "34,43",
                    "34,42",
                    "34,41",
                    "33,41",
                    "32,41",
                    "31,41"
                ]
            },
            {
                "location": "8,6",
                "output": 30.48448777,
                "cables": [
                    "8,6",
                    "8,5",
                    "8,4",
                    "9,4",
                    "10,4",
                    "11,4",
                    "12,4",
                    "13,4",
                    "14,4",
                    "15,4"
                ]
            },
            {
                "location": "9,37",
                "output": 63.19785578,
                "cables": [
                    "9,37",
                    "9,36",
                    "9,35",
                    "9,34",
                    "9,33",
                    "9,32",
                    "9,31",
                    "9,30",
                    "9,29",
                    "9,28",
                    "9,27"
                ]
            },
            {
                "location": "21,37",
                "output": 53.84443114,
                "cables": [
                    "21,37",
                    "21,36",
                    "21,35",
                    "21,34",
                    "21,33",
                    "21,32",
                    "21,31",
                    "21,30",
                    "21,29"
                ]
            },
            {
                "location": "27,22",
                "output": 29.92408755,
                "cables": [
                    "27,22",
                    "28,22",
                    "29,22",
                    "30,22",
                    "31,22",
                    "32,22",
                    "33,22",
                    "34,22",
                    "35,22",
                    "36,22",
                    "37,22",
                    "38,22"
                ]
            },
            {
                "location": "38,22",
                "output": 59.91115918,
                "cables": [
                    "38,22",
                    "38,21",
                    "38,20",
                    "38,19",
                    "38,18"
                ]
            },
            {
                "location": "30,37",
                "output": 61.05026554,
                "cables": [
                    "30,37",
                    "30,36",
                    "29,36",
                    "28,36",
                    "27,36",
                    "26,36",
                    "25,36",
                    "24,36"
                ]
            },
            {
                "location": "31,41",
                "output": 68.6532457,
                "cables": [
                    "31,41",
                    "31,40",
                    "31,39",
                    "31,38",
                    "31,37",
                    "30,37"
                ]
            },
            {
                "location": "21,29",
                "output": 45.33453242,
                "cables": [
                    "21,29",
                    "21,28",
                    "21,27",
                    "22,27",
                    "23,27",
                    "24,27",
                    "25,27",
                    "26,27"
                ]
            },
            {
                "location": "27,3",
                "output": 57.11814462,
                "cables": [
                    "27,3",
                    "28,3",
                    "29,3",
                    "30,3"
                ]
            },
            {
                "location": "23,10",
                "output": 29.34726889,
                "cables": [
                    "23,10",
                    "23,9",
                    "23,8",
                    "23,7",
                    "23,6",
                    "23,5",
                    "24,5",
                    "25,5"
                ]
            },
            {
                "location": "2,50",
                "output": 29.93133051,
                "cables": [
                    "2,50",
                    "2,49",
                    "2,48",
                    "2,47",
                    "2,46",
                    "2,45",
                    "2,44",
                    "2,43",
                    "2,42",
                    "2,41",
                    "2,40",
                    "2,39",
                    "2,38",
                    "2,37",
                    "2,36",
                    "2,35",
                    "2,34"
                ]
            },
            {
                "location": "30,2",
                "output": 60.7690834,
                "cables": [
                    "30,2",
                    "30,3",
                    "30,4",
                    "30,5",
                    "30,6",
                    "30,7",
                    "30,8",
                    "31,8",
                    "32,8",
                    "33,8",
                    "34,8"
                ]
            },
            {
                "location": "15,4",
                "output": 70.02856894,
                "cables": [
                    "15,4",
                    "15,3",
                    "16,3",
                    "17,3",
                    "18,3",
                    "19,3"
                ]
            },
            {
                "location": "18,15",
                "output": 57.15314373,
                "cables": [
                    "18,15",
                    "18,14",
                    "19,14",
                    "20,14",
                    "21,14",
                    "22,14"
                ]
            },
            {
                "location": "25,5",
                "output": 55.93567156,
                "cables": [
                    "25,5",
                    "25,4",
                    "25,3",
                    "26,3",
                    "27,3"
                ]
            },
            {
                "location": "0,34",
                "output": 74.53947279,
                "cables": [
                    "0,34",
                    "1,34",
                    "2,34",
                    "3,34",
                    "4,34",
                    "5,34",
                    "6,34",
                    "7,34",
                    "8,34",
                    "9,34"
                ]
            },
            {
                "location": "10,39",
                "output": 46.25506287,
                "cables": [
                    "10,39",
                    "10,38",
                    "10,37",
                    "9,37"
                ]
            },
            {
                "location": "47,50",
                "output": 70.41480105,
                "cables": [
                    "47,50",
                    "47,49",
                    "47,48",
                    "47,47",
                    "46,47",
                    "45,47",
                    "44,47",
                    "43,47",
                    "42,47"
                ]
            },
            {
                "location": "42,47",
                "output": 26.65336877,
                "cables": [
                    "42,47",
                    "41,47",
                    "40,47",
                    "39,47",
                    "38,47",
                    "37,47",
                    "36,47",
                    "35,47",
                    "34,47"
                ]
            },
            {
                "location": "7,25",
                "output": 38.50460131,
                "cables": [
                    "7,25",
                    "7,26",
                    "7,27",
                    "8,27",
                    "9,27",
                    "10,27"
                ]
            },
            {
                "location": "38,18",
                "output": 69.53106382,
                "cables": [
                    "38,18",
                    "38,17",
                    "38,16",
                    "38,15",
                    "38,14",
                    "38,13",
                    "38,12"
                ]
            },
            {
                "location": "34,8",
                "output": 41.23924682,
                "cables": [
                    "34,8",
                    "34,9",
                    "34,10",
                    "34,11",
                    "34,12",
                    "35,12",
                    "36,12",
                    "37,12",
                    "38,12"
                ]
            },
            {
                "location": "19,3",
                "output": 70.34144168,
                "cables": [
                    "19,3",
                    "20,3",
                    "21,3",
                    "22,3",
                    "23,3",
                    "24,3",
                    "25,3"
                ]
            },
            {
                "location": "24,24",
                "output": 52.07076394,
                "cables": [
                    "24,24",
                    "24,23",
                    "24,22",
                    "25,22",
                    "26,22",
                    "27,22"
                ]
            },
            {
                "location": "24,36",
                "output": 63.12900053,
                "cables": [
                    "24,36",
                    "23,36",
                    "22,36",
                    "21,36"
                ]
            },
            {
                "location": "22,14",
                "output": 42.32972013,
                "cables": [
                    "22,14",
                    "22,13",
                    "22,12",
                    "22,11",
                    "22,10",
                    "23,10"
                ]
            },
            {
                "location": "26,27",
                "output": 56.65609954,
                "cables": [
                    "26,27",
                    "26,26",
                    "26,25",
                    "26,24",
                    "25,24",
                    "24,24"
                ]
            },
            {
                "location": "10,27",
                "output": 26.19979919,
                "cables": [
                    "10,27",
                    "11,27",
                    "12,27",
                    "13,27",
                    "14,27",
                    "15,27",
                    "16,27",
                    "17,27",
                    "18,27",
                    "19,27",
                    "20,27",
                    "21,27"
                ]
            }
        ]
    },
    {
        "location": "43,13",
        "capacity": 1507.0,
        "houses": [
            {
                "location": "24,22",
                "output": 66.13020717,
                "cables": [
                    "24,22",
                    "25,22",
                    "26,22",
                    "27,22",
                    "28,22",
                    "29,22",
                    "30,22"
                ]
            },
            {
                "location": "19,38",
                "output": 46.4333204,
                "cables": [
                    "19,38",
                    "19,37",
                    "19,36",
                    "19,35",
                    "19,34",
                    "20,34"
                ]
            },
            {
                "location": "33,7",
                "output": 39.45690812,
                "cables": [
                    "33,7",
                    "33,8",
                    "33,9",
                    "32,9"
                ]
            },
            {
                "location": "47,6",
                "output": 41.78571625,
                "cables": [
                    "47,6",
                    "47,7",
                    "47,8",
                    "47,9",
                    "47,10",
                    "47,11",
                    "47,12",
                    "47,13"
                ]
            },
            {
                "location": "26,30",
                "output": 62.0133643,
                "cables": [
                    "26,30",
                    "27,30",
                    "28,30",
                    "29,30",
                    "30,30"
                ]
            },
            {
                "location": "5,15",
                "output": 52.08494864,
                "cables": [
                    "5,15",
                    "6,15",
                    "7,15",
                    "8,15",
                    "9,15",
                    "10,15",
                    "11,15",
                    "12,15",
                    "13,15",
                    "14,15",
                    "15,15",
                    "16,15",
                    "17,15",
                    "18,15",
                    "19,15",
                    "20,15"
                ]
            },
            {
                "location": "30,12",
                "output": 66.05341632,
                "cables": [
                    "30,12",
                    "31,12",
                    "32,12",
                    "33,12"
                ]
            },
            {
                "location": "20,14",
                "output": 45.14508246,
                "cables": [
                    "20,14",
                    "20,15",
                    "21,15",
                    "22,15",
                    "23,15",
                    "24,15",
                    "25,15",
                    "26,15",
                    "27,15",
                    "28,15",
                    "29,15",
                    "30,15"
                ]
            },
            {
                "location": "43,32",
                "output": 46.63929091,
                "cables": [
                    "43,32",
                    "43,31",
                    "43,30",
                    "43,29",
                    "43,28",
                    "43,27",
                    "43,26",
                    "43,25",
                    "43,24",
                    "44,24",
                    "45,24"
                ]
            },
            {
                "location": "37,47",
                "output": 26.27681146,
                "cables": [
                    "37,47",
                    "37,46",
                    "37,45",
                    "37,44",
                    "37,43",
                    "37,42",
                    "37,41",
                    "37,40",
                    "38,40",
                    "39,40",
                    "40,40",
                    "41,40",
                    "42,40"
                ]
            },
            {
                "location": "4,38",
                "output": 28.04976611,
                "cables": [
                    "4,38",
                    "4,39",
                    "4,40",
                    "4,41",
                    "4,42",
                    "5,42",
                    "6,42",
                    "7,42",
                    "8,42",
                    "9,42",
                    "10,42",
                    "11,42",
                    "12,42",
                    "13,42",
                    "14,42",
                    "15,42"
                ]
            },
            {
                "location": "47,16",
                "output": 31.4973607,
                "cables": [
                    "47,16",
                    "47,15",
                    "47,14",
                    "47,13",
                    "46,13",
                    "45,13",
                    "44,13",
                    "43,13"
                ]
            },
            {
                "location": "1,18",
                "output": 45.25994244,
                "cables": [
                    "1,18",
                    "1,17",
                    "1,16",
                    "1,15"
                ]
            },
            {
                "location": "30,16",
                "output": 49.93687743,
                "cables": [
                    "30,16",
                    "30,15",
                    "31,15"
                ]
            },
            {
                "location": "21,42",
                "output": 65.6434655,
                "cables": [
                    "21,42",
                    "21,41",
                    "21,40",
                    "21,39",
                    "21,38",
                    "20,38",
                    "19,38"
                ]
            },
            {
                "location": "0,16",
                "output": 48.15325636,
                "cables": [
                    "0,16",
                    "0,15",
                    "1,15",
                    "2,15",
                    "3,15",
                    "4,15",
                    "5,15"
                ]
            },
            {
                "location": "31,18",
                "output": 38.85647001,
                "cables": [
                    "31,18",
                    "31,17",
                    "31,16",
                    "31,15"
                ]
            },
            {
                "location": "45,24",
                "output": 31.97506792,
                "cables": [
                    "45,24",
                    "45,23",
                    "45,22",
                    "45,21",
                    "45,20",
                    "45,19",
                    "45,18",
                    "45,17",
                    "45,16",
                    "46,16",
                    "47,16"
                ]
            },
            {
                "location": "3,9",
                "output": 53.27408283,
                "cables": [
                    "3,9",
                    "3,10",
                    "3,11",
                    "3,12",
                    "3,13",
                    "3,14",
                    "3,15"
                ]
            },
            {
                "location": "50,3",
                "output": 60.5787997,
                "cables": [
                    "50,3",
                    "50,4",
                    "50,5",
                    "50,6",
                    "49,6",
                    "48,6",
                    "47,6"
                ]
            },
            {
                "location": "32,9",
                "output": 32.56142196,
                "cables": [
                    "32,9",
                    "32,10",
                    "32,11",
                    "32,12"
                ]
            },
            {
                "location": "18,33",
                "output": 64.25056806,
                "cables": [
                    "18,33",
                    "19,33",
                    "20,33"
                ]
            },
            {
                "location": "30,31",
                "output": 33.30314048,
                "cables": [
                    "30,31",
                    "30,30",
                    "30,29",
                    "30,28",
                    "30,27",
                    "30,26",
                    "30,25"
                ]
            },
            {
                "location": "33,11",
                "output": 66.45865072,
                "cables": [
                    "33,11",
                    "33,12",
                    "33,13",
                    "34,13",
                    "35,13",
                    "36,13",
                    "37,13",
                    "38,13",
                    "39,13",
                    "40,13",
                    "41,13",
                    "42,13",
                    "43,13"
                ]
            },
            {
                "location": "15,46",
                "output": 63.30973309,
                "cables": [
                    "15,46",
                    "15,45",
                    "15,44",
                    "15,43",
                    "15,42",
                    "16,42",
                    "17,42",
                    "18,42",
                    "19,42",
                    "20,42",
                    "21,42"
                ]
            },
            {
                "location": "31,15",
                "output": 39.85726456,
                "cables": [
                    "31,15",
                    "31,14",
                    "31,13",
                    "31,12"
                ]
            },
            {
                "location": "42,40",
                "output": 41.46231813,
                "cables": [
                    "42,40",
                    "42,39",
                    "42,38",
                    "42,37",
                    "42,36",
                    "42,35",
                    "42,34"
                ]
            },
            {
                "location": "16,3",
                "output": 33.61818802,
                "cables": [
                    "16,3",
                    "15,3",
                    "14,3",
                    "13,3",
                    "12,3",
                    "11,3",
                    "10,3",
                    "9,3",
                    "8,3",
                    "7,3",
                    "6,3",
                    "5,3",
                    "4,3"
                ]
            },
            {
                "location": "20,34",
                "output": 44.9319234,
                "cables": [
                    "20,34",
                    "20,33",
                    "20,32",
                    "20,31",
                    "20,30",
                    "21,30",
                    "22,30",
                    "23,30",
                    "24,30",
                    "25,30",
                    "26,30"
                ]
            },
            {
                "location": "30,25",
                "output": 63.13649746,
                "cables": [
                    "30,25",
                    "30,24",
                    "30,23",
                    "30,22",
                    "30,21",
                    "30,20",
                    "30,19",
                    "30,18",
                    "31,18"
                ]
            },
            {
                "location": "42,34",
                "output": 43.0013272,
                "cables": [
                    "42,34",
                    "42,33",
                    "42,32",
                    "43,32"
                ]
            },
            {
                "location": "4,0",
                "output": 29.86780761,
                "cables": [
                    "4,0",
                    "4,1",
                    "4,2",
                    "4,3",
                    "4,4",
                    "4,5",
                    "4,6",
                    "4,7",
                    "4,8",
                    "4,9",
                    "3,9"
                ]
            }
        ]
    },
    {
        "location": "49,23",
        "capacity": 1507.0,
        "houses": [
            {
                "location": "17,11",
                "output": 62.14055349,
                "cables": [
                    "17,11",
                    "18,11",
                    "19,11",
                    "20,11",
                    "21,11"
                ]
            },
            {
                "location": "16,38",
                "output": 65.00367928,
                "cables": [
                    "16,38",
                    "16,37",
                    "17,37",
                    "18,37"
                ]
            },
            {
                "location": "37,28",
                "output": 60.40913294,
                "cables": [
                    "37,28",
                    "37,27",
                    "37,26",
                    "37,25",
                    "37,24",
                    "38,24"
                ]
            },
            {
                "location": "2,8",
                "output": 27.78076375,
                "cables": [
                    "2,8",
                    "2,7",
                    "2,6",
                    "2,5",
                    "2,4",
                    "3,4",
                    "4,4",
                    "5,4",
                    "6,4",
                    "7,4",
                    "8,4"
                ]
            },
            {
                "location": "23,48",
                "output": 57.77286486,
                "cables": [
                    "23,48",
                    "22,48",
                    "21,48"
                ]
            },
            {
                "location": "28,23",
                "output": 38.72179636,
                "cables": [
                    "28,23",
                    "28,24",
                    "29,24",
                    "30,24",
                    "31,24",
                    "32,24",
                    "33,24",
                    "34,24",
                    "35,24",
                    "36,24",
                    "37,24"
                ]
            },
            {
                "location": "18,37",
                "output": 70.21473166,
                "cables": [
                    "18,37",
                    "18,36",
                    "18,35",
                    "18,34",
                    "18,33",
                    "19,33"
                ]
            },
            {
                "location": "4,33",
                "output": 38.13617191,
                "cables": [
                    "4,33",
                    "4,34",
                    "4,35",
                    "4,36",
                    "4,37",
                    "4,38",
                    "5,38",
                    "6,38",
                    "7,38",
                    "8,38",
                    "9,38",
                    "10,38",
                    "11,38"
                ]
            },
            {
                "location": "15,44",
                "output": 53.08761347,
                "cables": [
                    "15,44",
                    "15,43",
                    "15,42",
                    "15,41",
                    "16,41"
                ]
            },
            {
                "location": "21,50",
                "output": 38.71047582,
                "cables": [
                    "21,50",
                    "21,49",
                    "21,48"
                ]
            },
            {
                "location": "11,4",
                "output": 44.75870431,
                "cables": [
                    "11,4",
                    "12,4",
                    "13,4",
                    "14,4",
                    "15,4",
                    "16,4",
                    "17,4",
                    "18,4",
                    "19,4",
                    "20,4"
                ]
            },
            {
                "location": "8,3",
                "output": 31.03872389,
                "cables": [
                    "8,3",
                    "8,4",
                    "9,4",
                    "10,4",
                    "11,4"
                ]
            },
            {
                "location": "30,4",
                "output": 29.51140333,
                "cables": [
                    "30,4",
                    "29,4",
                    "28,4",
                    "27,4",
                    "26,4",
                    "25,4",
                    "24,4",
                    "23,4",
                    "22,4",
                    "21,4",
                    "20,4"
                ]
            },
            {
                "location": "45,1",
                "output": 59.63813712,
                "cables": [
                    "45,1",
                    "45,2",
                    "45,3",
                    "45,4",
                    "44,4",
                    "43,4",
                    "42,4",
                    "41,4",
                    "40,4",
                    "39,4",
                    "38,4",
                    "37,4"
                ]
            },
            {
                "location": "9,44",
                "output": 44.14228862,
                "cables": [
                    "9,44",
                    "10,44",
                    "11,44",
                    "12,44",
                    "13,44",
                    "14,44",
                    "15,44"
                ]
            },
            {
                "location": "44,27",
                "output": 28.73871494,
                "cables": [
                    "44,27",
                    "44,26",
                    "44,25",
                    "44,24",
                    "44,23",
                    "45,23",
                    "46,23",
                    "47,23",
                    "48,23",
                    "49,23"
                ]
            },
            {
                "location": "11,38",
                "output": 74.82543524,
                "cables": [
                    "11,38",
                    "12,38",
                    "13,38",
                    "14,38",
                    "15,38",
                    "16,38"
                ]
            },
            {
                "location": "16,41",
                "output": 34.78697213,
                "cables": [
                    "16,41",
                    "16,40",
                    "16,39",
                    "16,38"
                ]
            },
            {
                "location": "19,40",
                "output": 60.03957103,
                "cables": [
                    "19,40",
                    "18,40",
                    "17,40",
                    "16,40"
                ]
            },
            {
                "location": "24,18",
                "output": 38.3766668,
                "cables": [
                    "24,18",
                    "24,19",
                    "24,20",
                    "24,21",
                    "24,22",
                    "24,23",
                    "25,23",
                    "26,23",
                    "27,23",
                    "28,23"
                ]
            },
            {
                "location": "21,11",
                "output": 47.29043731,
                "cables": [
                    "21,11",
                    "21,12",
                    "21,13",
                    "21,14",
                    "21,15",
                    "21,16",
                    "21,17",
                    "22,17"
                ]
            },
            {
                "location": "20,3",
                "output": 67.12368936,
                "cables": [
                    "20,3",
                    "20,4",
                    "20,5",
                    "20,6",
                    "20,7",
                    "20,8",
                    "20,9",
                    "20,10",
                    "20,11"
                ]
            },
            {
                "location": "27,13",
                "output": 72.11411933,
                "cables": [
                    "27,13",
                    "26,13",
                    "25,13",
                    "24,13",
                    "23,13",
                    "22,13",
                    "21,13"
                ]
            },
            {
                "location": "38,24",
                "output": 50.53984719,
                "cables": [
                    "38,24",
                    "39,24",
                    "40,24",
                    "41,24",
                    "42,24",
                    "43,24",
                    "44,24"
                ]
            },
            {
                "location": "24,30",
                "output": 76.1538049,
                "cables": [
                    "24,30",
                    "24,29",
                    "24,28",
                    "24,27",
                    "24,26",
                    "24,25",
                    "24,24",
                    "24,23"
                ]
            },
            {
                "location": "19,33",
                "output": 66.97873982,
                "cables": [
                    "19,33",
                    "19,32",
                    "19,31",
                    "19,30",
                    "20,30",
                    "21,30",
                    "22,30",
                    "23,30",
                    "24,30"
                ]
            },
            {
                "location": "37,6",
                "output": 30.41692196,
                "cables": [
                    "37,6",
                    "37,5",
                    "37,4",
                    "36,4",
                    "35,4",
                    "34,4",
                    "33,4",
                    "32,4",
                    "31,4",
                    "30,4"
                ]
            },
            {
                "location": "21,48",
                "output": 71.35472201,
                "cables": [
                    "21,48",
                    "21,47",
                    "21,46",
                    "21,45",
                    "21,44",
                    "21,43",
                    "21,42",
                    "21,41",
                    "21,40",
                    "20,40",
                    "19,40"
                ]
            },
            {
                "location": "22,17",
                "output": 66.78438663,
                "cables": [
                    "22,17",
                    "22,18",
                    "23,18",
                    "24,18"
                ]
            }
        ]
    },
    {
        "location": "42,3",
        "capacity": 1507.0,
        "houses": [
            {
                "location": "19,4",
                "output": 52.43116675,
                "cables": [
                    "19,4",
                    "19,5",
                    "19,6",
                    "19,7",
                    "19,8",
                    "19,9",
                    "19,10",
                    "20,10",
                    "21,10",
                    "22,10"
                ]
            },
            {
                "location": "47,40",
                "output": 71.42208448,
                "cables": [
                    "47,40",
                    "47,39",
                    "47,38",
                    "47,37",
                    "47,36",
                    "47,35"
                ]
            },
            {
                "location": "23,1",
                "output": 37.23961036,
                "cables": [
                    "23,1",
                    "23,2",
                    "23,3",
                    "23,4",
                    "22,4",
                    "21,4",
                    "20,4",
                    "19,4"
                ]
            },
            {
                "location": "16,48",
                "output": 29.83002147,
                "cables": [
                    "16,48",
                    "16,47",
                    "16,46",
                    "16,45",
                    "16,44",
                    "16,43",
                    "16,42",
                    "16,41",
                    "16,40",
                    "17,40",
                    "18,40",
                    "19,40",
                    "20,40",
                    "21,40",
                    "22,40",
                    "23,40",
                    "24,40",
                    "25,40"
                ]
            },
            {
                "location": "12,5",
                "output": 74.15296092,
                "cables": [
                    "12,5",
                    "13,5",
                    "14,5",
                    "15,5",
                    "16,5",
                    "17,5",
                    "18,5",
                    "19,5"
                ]
            },
            {
                "location": "50,35",
                "output": 54.25835415,
                "cables": [
                    "50,35",
                    "49,35",
                    "48,35",
                    "47,35",
                    "46,35",
                    "45,35",
                    "44,35"
                ]
            },
            {
                "location": "9,48",
                "output": 41.7880369,
                "cables": [
                    "9,48",
                    "10,48",
                    "11,48",
                    "12,48",
                    "13,48",
                    "14,48",
                    "15,48",
                    "16,48"
                ]
            },
            {
                "location": "22,10",
                "output": 72.88165705,
                "cables": [
                    "22,10",
                    "22,11",
                    "22,12",
                    "22,13",
                    "22,14",
                    "22,15",
                    "22,16",
                    "22,17",
                    "22,18",
                    "22,19",
                    "22,20",
                    "22,21",
                    "22,22",
                    "22,23",
                    "22,24",
                    "22,25",
                    "22,26",
                    "22,27"
                ]
            },
            {
                "location": "48,4",
                "output": 58.90934923,
                "cables": [
                    "48,4",
                    "48,3",
                    "47,3",
                    "46,3",
                    "45,3",
                    "44,3",
                    "43,3",
                    "42,3"
                ]
            },
            {
                "location": "28,37",
                "output": 55.74063546,
                "cables": [
                    "28,37",
                    "28,36",
                    "28,35",
                    "28,34",
                    "28,33",
                    "28,32",
                    "28,31",
                    "28,30",
                    "29,30"
                ]
            },
            {
                "location": "4,3",
                "output": 45.9393011,
                "cables": [
                    "4,3",
                    "4,4",
                    "4,5"
                ]
            },
            {
                "location": "11,10",
                "output": 63.87594515,
                "cables": [
                    "11,10",
                    "11,9",
                    "11,8",
                    "11,7",
                    "11,6",
                    "11,5",
                    "12,5"
                ]
            },
            {
                "location": "9,50",
                "output": 38.5524821,
                "cables": [
                    "9,50",
                    "9,49",
                    "9,48"
                ]
            },
            {
                "location": "40,39",
                "output": 40.72933179,
                "cables": [
                    "40,39",
                    "40,38",
                    "40,37",
                    "40,36",
                    "40,35",
                    "39,35"
                ]
            },
            {
                "location": "25,40",
                "output": 67.70113184,
                "cables": [
                    "25,40",
                    "25,39",
                    "25,38",
                    "25,37",
                    "26,37"
                ]
            },
            {
                "location": "29,22",
                "output": 56.03511409,
                "cables": [
                    "29,22",
                    "30,22",
                    "31,22",
                    "32,22",
                    "33,22"
                ]
            },
            {
                "location": "21,27",
                "output": 38.69411298,
                "cables": [
                    "21,27",
                    "22,27",
                    "23,27",
                    "24,27",
                    "25,27",
                    "26,27",
                    "27,27",
                    "28,27",
                    "29,27"
                ]
            },
            {
                "location": "37,35",
                "output": 29.26065385,
                "cables": [
                    "37,35",
                    "36,35",
                    "35,35",
                    "34,35",
                    "33,35",
                    "32,35",
                    "31,35",
                    "30,35",
                    "29,35",
                    "28,35"
                ]
            },
            {
                "location": "39,43",
                "output": 39.37298309,
                "cables": [
                    "39,43",
                    "39,42",
                    "39,41",
                    "39,40",
                    "39,39",
                    "40,39"
                ]
            },
            {
                "location": "39,19",
                "output": 64.25603513,
                "cables": [
                    "39,19",
                    "39,18",
                    "39,17",
                    "39,16",
                    "39,15",
                    "39,14"
                ]
            },
            {
                "location": "29,30",
                "output": 62.33504063,
                "cables": [
                    "29,30",
                    "29,29",
                    "29,28",
                    "29,27",
                    "29,26",
                    "29,25",
                    "29,24",
                    "29,23",
                    "29,22"
                ]
            },
            {
                "location": "44,33",
                "output": 51.84271486,
                "cables": [
                    "44,33",
                    "44,34",
                    "44,35",
                    "43,35",
                    "42,35",
                    "41,35",
                    "40,35"
                ]
            },
            {
                "location": "3,7",
                "output": 58.40033018,
                "cables": [
                    "3,7",
                    "3,6",
                    "3,5",
                    "4,5"
                ]
            },
            {
                "location": "38,21",
                "output": 33.56390131,
                "cables": [
                    "38,21",
                    "38,20",
                    "38,19",
                    "39,19"
                ]
            },
            {
                "location": "26,37",
                "output": 33.96614241,
                "cables": [
                    "26,37",
                    "27,37",
                    "28,37"
                ]
            },
            {
                "location": "39,35",
                "output": 26.81272998,
                "cables": [
                    "39,35",
                    "38,35",
                    "37,35"
                ]
            },
            {
                "location": "4,5",
                "output": 43.28587772,
                "cables": [
                    "4,5",
                    "5,5",
                    "6,5",
                    "7,5",
                    "8,5",
                    "9,5",
                    "10,5",
                    "11,5"
                ]
            },
            {
                "location": "36,41",
                "output": 29.1671214,
                "cables": [
                    "36,41",
                    "37,41",
                    "38,41",
                    "39,41"
                ]
            },
            {
                "location": "33,24",
                "output": 74.26615041,
                "cables": [
                    "33,24",
                    "33,23",
                    "33,22",
                    "33,21",
                    "34,21",
                    "35,21",
                    "36,21",
                    "37,21",
                    "38,21"
                ]
            },
            {
                "location": "39,14",
                "output": 49.16852893,
                "cables": [
                    "39,14",
                    "39,13",
                    "39,12",
                    "39,11",
                    "39,10",
                    "39,9",
                    "39,8",
                    "39,7",
                    "39,6",
                    "39,5",
                    "39,4",
                    "39,3",
                    "40,3",
                    "41,3",
                    "42,3"
                ]
            }
        ]
    }
]